miffi/__init__.py
miffi/__main__.py
miffi/_version.py
miffi/categorize.py
miffi/datasets.py
miffi/download.py
miffi/inference.py
miffi/parameters.py
miffi/utils.py
miffi/write_png.py
miffi-1.0.1.dist-info/LICENSE
miffi-1.0.1.dist-info/METADATA
miffi-1.0.1.dist-info/WHEEL
miffi-1.0.1.dist-info/entry_points.txt
miffi-1.0.1.dist-info/top_level.txt
miffi-1.0.1.dist-info/RECORD
