Metadata-Version: 2.1
Name: miffi
Version: 1.0.1
Summary: cryo-EM micrograph filtering utilizing Fourier space information
Author-email: Da Xu <dx63@cornell.edu>
Classifier: License :: OSI Approved :: GNU General Public License v3 (GPLv3)
Classifier: Programming Language :: Python :: 3
Requires-Python: >=3.8
License-File: LICENSE
Requires-Dist: pyyaml
Requires-Dist: starfile
Requires-Dist: mrcfile
Requires-Dist: torch >=1.13.1
Requires-Dist: torchvision
Requires-Dist: numpy
Requires-Dist: tqdm
Requires-Dist: matplotlib
Requires-Dist: timm >=0.5.4
Requires-Dist: ipywidgets
Requires-Dist: jupyterlab
